tinify/__init__.py
tinify/_typed.py
tinify/client.py
tinify/errors.py
tinify/py.typed
tinify/result.py
tinify/result_meta.py
tinify/source.py
tinify/version.py
tinify/data/cacert.pem
tinify-1.7.1.dist-info/licenses/LICENSE
tinify-1.7.1.dist-info/METADATA
tinify-1.7.1.dist-info/WHEEL
tinify-1.7.1.dist-info/top_level.txt
tinify-1.7.1.dist-info/RECORD
